Metadata-Version: 2.1
Name: ehrimage
Version: 0.0.dev1
Summary: Data Science Toolkit for Healthcare Images
Author-email: name <author@example.com>
Classifier: Programming Language :: Python :: 3
Classifier: License :: OSI Approved :: MIT License
Classifier: Operating System :: OS Independent
Requires-Python: >=3.11
License-File: LICENSE
Requires-Dist: wasabi
Requires-Dist: opencv-python
Requires-Dist: torch
Requires-Dist: torchvision
Provides-Extra: dev
Requires-Dist: pytest ; extra == 'dev'
Requires-Dist: build ; extra == 'dev'
Requires-Dist: twine ; extra == 'dev'
Requires-Dist: jupyter ; extra == 'dev'
Requires-Dist: uv ; extra == 'dev'
